pybbox2/__init__.py
pybbox2/bbox_api.py
pybbox2/bbox_api_endpoints.py
pybbox2/bbox_requests.py
pybbox2-0.2.3.dist-info/LICENSE.txt
pybbox2-0.2.3.dist-info/METADATA
pybbox2-0.2.3.dist-info/WHEEL
pybbox2-0.2.3.dist-info/top_level.txt
pybbox2-0.2.3.dist-info/RECORD
