Metadata-Version: 2.1
Name: pybbox2
Version: 0.2.3
Summary: A thin API wrapper for the french Bouygues router Bbox
Home-page: https://github.com/Salamandar/pybbox2
Author: Salamandar
Author-email: felix@piedallu.me
License: UNKNOWN
Project-URL: Bug Tracker, https://github.com/Salamandar/pybbox2/issues
Platform: UNKNOWN
Classifier: Programming Language :: Python :: 3
Classifier: License :: OSI Approved :: MIT License
Classifier: Operating System :: OS Independent
Requires-Python: >=3.6
License-File: LICENSE.txt
